LICENSE
README.md
setup.cfg
setup.py
bin/csvalign
bin/csvcsv
bin/csvcut
bin/csvgrep
bin/csvread
bin/csvsql
lib/csvmagic/__init__.py
lib/csvmagic/libcsv.py
lib/csvmagic.egg-info/PKG-INFO
lib/csvmagic.egg-info/SOURCES.txt
lib/csvmagic.egg-info/dependency_links.txt
lib/csvmagic.egg-info/requires.txt
lib/csvmagic.egg-info/top_level.txt
lib/csvmagic/plugins/__init__.py
lib/csvmagic/plugins/fix.py
man/man1/csvalign.1
man/man1/csvcsv.1
man/man1/csvcut.1
man/man1/csvgrep.1
man/man1/csvread.1
man/man1/csvsql.1