Metadata-Version: 2.1
Name: csvmagic
Version: 2.2.2
Summary: CSV Utilities
Home-page: https://github.com/markuskimius/csvmagic
Author: Mark Kim
Author-email: markuskimius+py@gmail.com
License: Apache 2.0
Keywords: csv,text
License-File: LICENSE
